branchesv/__init__.py
branchesv/branches.py
branchesv/branchesvcmd.py
branchesv/utils.py
tests/__init__.py
tests/test_branchesv.py
tests/test_utils.py
tests/files/branches.json
branchesv-0.2.12.dist-info/AUTHORS.rst
branchesv-0.2.12.dist-info/LICENSE
branchesv-0.2.12.dist-info/METADATA
branchesv-0.2.12.dist-info/WHEEL
branchesv-0.2.12.dist-info/entry_points.txt
branchesv-0.2.12.dist-info/top_level.txt
branchesv-0.2.12.dist-info/RECORD
