Metadata-Version: 2.1
Name: branchesv
Version: 0.2.12
Summary: Python package to get the information of all the repos in a directory
Home-page: https://git.vauxoo.com/vauxoo/branchesv
Author: Vauxoo
Author-email: joseangel@vauxoo.com
License: ISCL
Keywords: branchesv
Classifier: Development Status :: 2 - Pre-Alpha
Classifier: Intended Audience :: Developers
Classifier: License :: OSI Approved :: ISC License (ISCL)
Classifier: Natural Language :: English
Classifier: Programming Language :: Python :: 2
Classifier: Programming Language :: Python :: 2.6
Classifier: Programming Language :: Python :: 2.7
Classifier: Programming Language :: Python :: 3
Classifier: Programming Language :: Python :: 3.3
Classifier: Programming Language :: Python :: 3.4
Classifier: Programming Language :: Python :: 3.5
License-File: LICENSE
License-File: AUTHORS.rst
Requires-Dist: click==6.6
Requires-Dist: simplejson==3.11.1
Requires-Dist: chardet
Requires-Dist: spur==0.3.18; python_version < "3.7"
Requires-Dist: six==1.15.0; python_version <= "3.10"
Requires-Dist: gitdb==0.6.4; python_version <= "3.3"
Requires-Dist: smmap==3.0.1; python_version <= "3.3"
Requires-Dist: gitpython==1.0.0; python_version <= "3.3"
Requires-Dist: gitpython==3.1.0; python_version > "3.3"
Requires-Dist: six==1.16.0; python_version >= "3.11"
Requires-Dist: spur==0.3.22; python_version >= "3.7"
